ctx_miner/README.md
ctx_miner/__init__.py
ctx_miner/core/__init__.py
ctx_miner/core/ctx_miner.py
ctx_miner/core/schemas.py
ctx_miner/managers/__init__.py
ctx_miner/managers/embedding_manager.py
ctx_miner/managers/falkordb_manager.py
ctx_miner/managers/llm_manager.py
ctx_miner/utils/__init__.py
ctx_miner/utils/helpers.py
ctx_miner/utils/logger.py
ctx_miner-0.1.0.dist-info/METADATA
ctx_miner-0.1.0.dist-info/WHEEL
ctx_miner-0.1.0.dist-info/RECORD
