Metadata-Version: 2.4
Name: ctx-miner
Version: 0.1.0
Summary: A library for context-aware conversational AI using graph databases
Author-email: hienhayho <hienhayho3002@gmail.com>
License: MIT
Keywords: context-mining,conversational-ai,falkordb,graph-database,graphiti
Classifier: Development Status :: 3 - Alpha
Classifier: Intended Audience :: Developers
Classifier: License :: OSI Approved :: MIT License
Classifier: Programming Language :: Python :: 3
Classifier: Programming Language :: Python :: 3.11
Classifier: Programming Language :: Python :: 3.12
Classifier: Topic :: Software Development :: Libraries :: Python Modules
Requires-Python: >=3.11
Requires-Dist: graphiti-core[falkordb]>=0.18.2
Requires-Dist: loguru>=0.7.0
Requires-Dist: python-dotenv>=1.0.0
Requires-Dist: redis>=5.0.0
Provides-Extra: dev
Requires-Dist: black>=23.0.0; extra == 'dev'
Requires-Dist: mypy>=1.0.0; extra == 'dev'
Requires-Dist: pytest-asyncio>=0.21.0; extra == 'dev'
Requires-Dist: pytest>=7.0.0; extra == 'dev'
Requires-Dist: ruff>=0.1.0; extra == 'dev'
